setup.py
Aritmeticas.egg-info/PKG-INFO
Aritmeticas.egg-info/SOURCES.txt
Aritmeticas.egg-info/dependency_links.txt
Aritmeticas.egg-info/top_level.txt
Mate/Aritmetica.py
Mate/__init__.py