Metadata-Version: 2.1
Name: Aritmeticas
Version: 1.0
Summary: Paquete que calcula funciones aritmaticas
Home-page: https://www.hektor.dev
Author: Martin Aguilar
Author-email: martin@gmail.com
License: UNKNOWN
Platform: UNKNOWN
